miniresponder/__init__.py
miniresponder/miniresponder.py
miniresponder/packets.py
miniresponder/settings.py
miniresponder/utils.py
miniresponder/poisoners/LLMNR.py
miniresponder/poisoners/MDNS.py
miniresponder/poisoners/NBTNS.py
miniresponder/poisoners/__init__.py
miniresponder/servers/HTTP.py
miniresponder/servers/SMB.py
miniresponder-0.1.0.dist-info/licenses/LICENSE
miniresponder-0.1.0.dist-info/METADATA
miniresponder-0.1.0.dist-info/WHEEL
miniresponder-0.1.0.dist-info/entry_points.txt
miniresponder-0.1.0.dist-info/top_level.txt
miniresponder-0.1.0.dist-info/RECORD
