Metadata-Version: 2.4
Name: miniresponder
Version: 0.1.0
Summary: A stripped-down Responder fork
Author-email: jrmdev <jrmdev@github.com>
License:                     GNU GENERAL PUBLIC LICENSE
Keywords: network,responder,poisoner,security
Classifier: Programming Language :: Python :: 3
Classifier: License :: OSI Approved :: GNU General Public License v3 (GPLv3)
Classifier: Operating System :: POSIX :: Linux
Requires-Python: >=3.8
License-File: LICENSE
Dynamic: license-file
